{"ID":"Brayden Patterson","startTime":"2018-11-29T18:35:38.828Z","endTime":"2018-11-29T18:57:20.126Z","data":[{"index":1,"src":"./assets/false/2-999.jpg","score":1,"duration_ms":2164,"startTime":"2018-11-29T18:36:18.332Z","endTime":"2018-11-29T18:36:20.496Z"},{"index":2,"src":"./assets/false/2-998.jpg","score":1,"duration_ms":1073,"startTime":"2018-11-29T18:36:27.511Z","endTime":"2018-11-29T18:36:28.584Z"},{"index":3,"src":"./assets/icons/2-012.jpg","score":0,"duration_ms":874,"startTime":"2018-11-29T18:36:35.600Z","endTime":"2018-11-29T18:36:36.474Z"},{"index":4,"src":"./assets/false/2-996.jpg","score":1,"duration_ms":828,"startTime":"2018-11-29T18:36:43.489Z","endTime":"2018-11-29T18:36:44.317Z"},{"index":5,"src":"./assets/false/2-995.jpg","score":1,"duration_ms":953,"startTime":"2018-11-29T18:36:51.345Z","endTime":"2018-11-29T18:36:52.298Z"},{"index":6,"src":"./assets/icons/2-022.jpg","score":1,"duration_ms":2865,"startTime":"2018-11-29T18:36:59.315Z","endTime":"2018-11-29T18:37:02.180Z"},{"index":7,"src":"./assets/icons/2-028.jpg","score":0,"duration_ms":18653,"startTime":"2018-11-29T18:37:09.198Z","endTime":"2018-11-29T18:37:27.851Z"},{"index":8,"src":"./assets/icons/2-032.jpg","score":1,"duration_ms":1097,"startTime":"2018-11-29T18:37:34.870Z","endTime":"2018-11-29T18:37:35.967Z"},{"index":9,"src":"./assets/icons/2-034.jpg","score":1,"duration_ms":1494,"startTime":"2018-11-29T18:37:42.987Z","endTime":"2018-11-29T18:37:44.481Z"},{"index":10,"src":"./assets/false/2-990.jpg","score":1,"duration_ms":997,"startTime":"2018-11-29T18:37:51.501Z","endTime":"2018-11-29T18:37:52.498Z"},{"index":11,"src":"./assets/false/2-989.jpg","score":1,"duration_ms":702,"startTime":"2018-11-29T18:37:59.526Z","endTime":"2018-11-29T18:38:00.228Z"},{"index":12,"src":"./assets/icons/2-045.jpg","score":1,"duration_ms":789,"startTime":"2018-11-29T18:38:07.241Z","endTime":"2018-11-29T18:38:08.030Z"},{"index":13,"src":"./assets/false/2-987.jpg","score":1,"duration_ms":1282,"startTime":"2018-11-29T18:38:15.055Z","endTime":"2018-11-29T18:38:16.337Z"},{"index":14,"src":"./assets/icons/2-055.jpg","score":1,"duration_ms":904,"startTime":"2018-11-29T18:38:23.357Z","endTime":"2018-11-29T18:38:24.261Z"},{"index":15,"src":"./assets/false/2-985.jpg","score":1,"duration_ms":865,"startTime":"2018-11-29T18:38:31.285Z","endTime":"2018-11-29T18:38:32.150Z"},{"index":16,"src":"./assets/icons/2-062.jpg","score":1,"duration_ms":1592,"startTime":"2018-11-29T18:38:39.170Z","endTime":"2018-11-29T18:38:40.762Z"},{"index":17,"src":"./assets/false/2-983.jpg","score":1,"duration_ms":701,"startTime":"2018-11-29T18:38:47.782Z","endTime":"2018-11-29T18:38:48.483Z"},{"index":18,"src":"./assets/icons/2-072.jpg","score":1,"duration_ms":2523,"startTime":"2018-11-29T18:38:55.507Z","endTime":"2018-11-29T18:38:58.030Z"},{"index":19,"src":"./assets/false/2-981.jpg","score":1,"duration_ms":731,"startTime":"2018-11-29T18:39:05.045Z","endTime":"2018-11-29T18:39:05.776Z"},{"index":20,"src":"./assets/icons/2-077.jpg","score":1,"duration_ms":987,"startTime":"2018-11-29T18:39:12.803Z","endTime":"2018-11-29T18:39:13.790Z"},{"index":21,"src":"./assets/false/2-979.jpg","score":1,"duration_ms":883,"startTime":"2018-11-29T18:39:20.811Z","endTime":"2018-11-29T18:39:21.694Z"},{"index":22,"src":"./assets/icons/1-002.jpg","score":1,"duration_ms":1233,"startTime":"2018-11-29T18:39:28.720Z","endTime":"2018-11-29T18:39:29.953Z"},{"index":23,"src":"./assets/false/1-998.jpg","score":1,"duration_ms":967,"startTime":"2018-11-29T18:39:36.978Z","endTime":"2018-11-29T18:39:37.945Z"},{"index":24,"src":"./assets/false/3-999.jpg","score":1,"duration_ms":901,"startTime":"2018-11-29T18:39:44.970Z","endTime":"2018-11-29T18:39:45.871Z"},{"index":25,"src":"./assets/false/3-998.jpg","score":1,"duration_ms":1135,"startTime":"2018-11-29T18:39:52.891Z","endTime":"2018-11-29T18:39:54.026Z"},{"index":26,"src":"./assets/icons/3-010.jpg","score":1,"duration_ms":930,"startTime":"2018-11-29T18:40:01.045Z","endTime":"2018-11-29T18:40:01.975Z"},{"index":27,"src":"./assets/false/3-996.jpg","score":1,"duration_ms":965,"startTime":"2018-11-29T18:40:08.994Z","endTime":"2018-11-29T18:40:09.959Z"},{"index":28,"src":"./assets/icons/3-018.jpg","score":1,"duration_ms":874,"startTime":"2018-11-29T18:40:16.983Z","endTime":"2018-11-29T18:40:17.857Z"},{"index":29,"src":"./assets/false/3-994.jpg","score":0,"duration_ms":3198,"startTime":"2018-11-29T18:40:24.879Z","endTime":"2018-11-29T18:40:28.077Z"},{"index":30,"src":"./assets/icons/3-028.jpg","score":1,"duration_ms":2258,"startTime":"2018-11-29T18:40:35.097Z","endTime":"2018-11-29T18:40:37.355Z"},{"index":31,"src":"./assets/false/3-992.jpg","score":1,"duration_ms":2155,"startTime":"2018-11-29T18:40:44.374Z","endTime":"2018-11-29T18:40:46.529Z"},{"index":32,"src":"./assets/icons/3-036.jpg","score":1,"duration_ms":847,"startTime":"2018-11-29T18:40:53.548Z","endTime":"2018-11-29T18:40:54.395Z"},{"index":33,"src":"./assets/false/3-990.jpg","score":1,"duration_ms":807,"startTime":"2018-11-29T18:41:01.408Z","endTime":"2018-11-29T18:41:02.215Z"},{"index":34,"src":"./assets/icons/3-043.jpg","score":0,"duration_ms":970,"startTime":"2018-11-29T18:41:09.238Z","endTime":"2018-11-29T18:41:10.208Z"},{"index":35,"src":"./assets/icons/3-046.jpg","score":1,"duration_ms":940,"startTime":"2018-11-29T18:41:17.225Z","endTime":"2018-11-29T18:41:18.165Z"},{"index":36,"src":"./assets/false/3-987.jpg","score":1,"duration_ms":1077,"startTime":"2018-11-29T18:41:25.187Z","endTime":"2018-11-29T18:41:26.264Z"},{"index":37,"src":"./assets/icons/3-055.jpg","score":1,"duration_ms":1611,"startTime":"2018-11-29T18:41:33.279Z","endTime":"2018-11-29T18:41:34.890Z"},{"index":38,"src":"./assets/false/3-985.jpg","score":1,"duration_ms":925,"startTime":"2018-11-29T18:41:41.907Z","endTime":"2018-11-29T18:41:42.832Z"},{"index":39,"src":"./assets/false/3-984.jpg","score":1,"duration_ms":1068,"startTime":"2018-11-29T18:41:49.852Z","endTime":"2018-11-29T18:41:50.920Z"},{"index":40,"src":"./assets/false/3-983.jpg","score":0,"duration_ms":1140,"startTime":"2018-11-29T18:41:57.934Z","endTime":"2018-11-29T18:41:59.074Z"},{"index":41,"src":"./assets/icons/3-072.jpg","score":1,"duration_ms":1030,"startTime":"2018-11-29T18:42:06.099Z","endTime":"2018-11-29T18:42:07.129Z"},{"index":42,"src":"./assets/icons/3-074.jpg","score":0,"duration_ms":821,"startTime":"2018-11-29T18:42:14.151Z","endTime":"2018-11-29T18:42:14.972Z"},{"index":43,"src":"./assets/icons/3-079.jpg","score":1,"duration_ms":774,"startTime":"2018-11-29T18:42:21.992Z","endTime":"2018-11-29T18:42:22.766Z"},{"index":44,"src":"./assets/icons/3-084.jpg","score":1,"duration_ms":1708,"startTime":"2018-11-29T18:42:29.786Z","endTime":"2018-11-29T18:42:31.494Z"},{"index":45,"src":"./assets/false/3-978.jpg","score":1,"duration_ms":849,"startTime":"2018-11-29T18:42:38.511Z","endTime":"2018-11-29T18:42:39.360Z"},{"index":46,"src":"./assets/icons/4-002.jpg","score":1,"duration_ms":725,"startTime":"2018-11-29T18:42:46.378Z","endTime":"2018-11-29T18:42:47.103Z"},{"index":47,"src":"./assets/false/4-998.jpg","score":1,"duration_ms":832,"startTime":"2018-11-29T18:42:54.125Z","endTime":"2018-11-29T18:42:54.957Z"},{"index":48,"src":"./assets/icons/4-012.jpg","score":1,"duration_ms":1976,"startTime":"2018-11-29T18:43:01.974Z","endTime":"2018-11-29T18:43:03.950Z"},{"index":49,"src":"./assets/false/4-996.jpg","score":1,"duration_ms":1219,"startTime":"2018-11-29T18:43:10.973Z","endTime":"2018-11-29T18:43:12.192Z"},{"index":50,"src":"./assets/icons/4-019.jpg","score":1,"duration_ms":1350,"startTime":"2018-11-29T18:43:19.214Z","endTime":"2018-11-29T18:43:20.564Z"},{"index":51,"src":"./assets/icons/4-021.jpg","score":1,"duration_ms":929,"startTime":"2018-11-29T18:43:27.584Z","endTime":"2018-11-29T18:43:28.513Z"},{"index":52,"src":"./assets/false/4-993.jpg","score":1,"duration_ms":1689,"startTime":"2018-11-29T18:43:35.531Z","endTime":"2018-11-29T18:43:37.220Z"},{"index":53,"src":"./assets/icons/4-030.jpg","score":1,"duration_ms":1199,"startTime":"2018-11-29T18:43:44.240Z","endTime":"2018-11-29T18:43:45.439Z"},{"index":54,"src":"./assets/false/4-991.jpg","score":1,"duration_ms":849,"startTime":"2018-11-29T18:43:52.454Z","endTime":"2018-11-29T18:43:53.303Z"},{"index":55,"src":"./assets/icons/4-037.jpg","score":1,"duration_ms":822,"startTime":"2018-11-29T18:44:00.330Z","endTime":"2018-11-29T18:44:01.152Z"},{"index":56,"src":"./assets/icons/4-042.jpg","score":1,"duration_ms":972,"startTime":"2018-11-29T18:44:08.168Z","endTime":"2018-11-29T18:44:09.140Z"},{"index":57,"src":"./assets/icons/4-045.jpg","score":1,"duration_ms":999,"startTime":"2018-11-29T18:44:16.159Z","endTime":"2018-11-29T18:44:17.158Z"},{"index":58,"src":"./assets/icons/4-051.jpg","score":1,"duration_ms":1344,"startTime":"2018-11-29T18:44:24.170Z","endTime":"2018-11-29T18:44:25.514Z"},{"index":59,"src":"./assets/icons/4-055.jpg","score":0,"duration_ms":1816,"startTime":"2018-11-29T18:44:32.534Z","endTime":"2018-11-29T18:44:34.350Z"},{"index":60,"src":"./assets/false/4-985.jpg","score":1,"duration_ms":1963,"startTime":"2018-11-29T18:44:41.364Z","endTime":"2018-11-29T18:44:43.327Z"},{"index":61,"src":"./assets/false/4-984.jpg","score":1,"duration_ms":979,"startTime":"2018-11-29T18:44:50.353Z","endTime":"2018-11-29T18:44:51.332Z"},{"index":62,"src":"./assets/icons/4-066.jpg","score":0,"duration_ms":3451,"startTime":"2018-11-29T18:44:58.354Z","endTime":"2018-11-29T18:45:01.805Z"},{"index":63,"src":"./assets/icons/4-069.jpg","score":1,"duration_ms":752,"startTime":"2018-11-29T18:45:08.814Z","endTime":"2018-11-29T18:45:09.566Z"},{"index":64,"src":"./assets/icons/4-073.jpg","score":1,"duration_ms":738,"startTime":"2018-11-29T18:45:16.580Z","endTime":"2018-11-29T18:45:17.318Z"},{"index":65,"src":"./assets/false/4-980.jpg","score":1,"duration_ms":1174,"startTime":"2018-11-29T18:45:24.338Z","endTime":"2018-11-29T18:45:25.512Z"},{"index":66,"src":"./assets/icons/4-082.jpg","score":0,"duration_ms":806,"startTime":"2018-11-29T18:45:32.533Z","endTime":"2018-11-29T18:45:33.339Z"},{"index":67,"src":"./assets/false/4-978.jpg","score":1,"duration_ms":1082,"startTime":"2018-11-29T18:45:40.359Z","endTime":"2018-11-29T18:45:41.441Z"},{"index":68,"src":"./assets/icons/4-090.jpg","score":0,"duration_ms":1612,"startTime":"2018-11-29T18:45:48.453Z","endTime":"2018-11-29T18:45:50.065Z"},{"index":69,"src":"./assets/icons/4-095.jpg","score":1,"duration_ms":2981,"startTime":"2018-11-29T18:45:57.085Z","endTime":"2018-11-29T18:46:00.066Z"},{"index":70,"src":"./assets/icons/4-098.jpg","score":1,"duration_ms":984,"startTime":"2018-11-29T18:46:07.073Z","endTime":"2018-11-29T18:46:08.057Z"},{"index":71,"src":"./assets/icons/4-102.jpg","score":1,"duration_ms":1597,"startTime":"2018-11-29T18:46:15.066Z","endTime":"2018-11-29T18:46:16.663Z"},{"index":72,"src":"./assets/false/4-973.jpg","score":1,"duration_ms":997,"startTime":"2018-11-29T18:46:23.685Z","endTime":"2018-11-29T18:46:24.682Z"},{"index":73,"src":"./assets/false/4-972.jpg","score":1,"duration_ms":1080,"startTime":"2018-11-29T18:46:31.700Z","endTime":"2018-11-29T18:46:32.780Z"},{"index":74,"src":"./assets/false/4-971.jpg","score":1,"duration_ms":955,"startTime":"2018-11-29T18:46:39.804Z","endTime":"2018-11-29T18:46:40.759Z"},{"index":75,"src":"./assets/icons/5-004.jpg","score":1,"duration_ms":935,"startTime":"2018-11-29T18:46:47.779Z","endTime":"2018-11-29T18:46:48.714Z"},{"index":76,"src":"./assets/icons/5-008.jpg","score":1,"duration_ms":752,"startTime":"2018-11-29T18:46:55.723Z","endTime":"2018-11-29T18:46:56.475Z"},{"index":77,"src":"./assets/false/5-997.jpg","score":1,"duration_ms":1105,"startTime":"2018-11-29T18:47:03.496Z","endTime":"2018-11-29T18:47:04.601Z"},{"index":78,"src":"./assets/false/5-996.jpg","score":1,"duration_ms":945,"startTime":"2018-11-29T18:47:11.626Z","endTime":"2018-11-29T18:47:12.571Z"},{"index":79,"src":"./assets/icons/5-018.jpg","score":1,"duration_ms":708,"startTime":"2018-11-29T18:47:19.585Z","endTime":"2018-11-29T18:47:20.293Z"},{"index":80,"src":"./assets/false/5-994.jpg","score":1,"duration_ms":1113,"startTime":"2018-11-29T18:47:27.307Z","endTime":"2018-11-29T18:47:28.420Z"},{"index":81,"src":"./assets/icons/5-026.jpg","score":1,"duration_ms":1124,"startTime":"2018-11-29T18:47:35.446Z","endTime":"2018-11-29T18:47:36.570Z"},{"index":82,"src":"./assets/icons/5-031.jpg","score":0,"duration_ms":1361,"startTime":"2018-11-29T18:47:43.582Z","endTime":"2018-11-29T18:47:44.943Z"},{"index":83,"src":"./assets/false/5-991.jpg","score":0,"duration_ms":852,"startTime":"2018-11-29T18:47:51.964Z","endTime":"2018-11-29T18:47:52.816Z"},{"index":84,"src":"./assets/false/5-990.jpg","score":1,"duration_ms":850,"startTime":"2018-11-29T18:47:59.842Z","endTime":"2018-11-29T18:48:00.692Z"},{"index":85,"src":"./assets/false/5-989.jpg","score":1,"duration_ms":862,"startTime":"2018-11-29T18:48:07.708Z","endTime":"2018-11-29T18:48:08.570Z"},{"index":86,"src":"./assets/icons/5-048.jpg","score":0,"duration_ms":751,"startTime":"2018-11-29T18:48:15.588Z","endTime":"2018-11-29T18:48:16.339Z"},{"index":87,"src":"./assets/icons/5-052.jpg","score":1,"duration_ms":1170,"startTime":"2018-11-29T18:48:23.357Z","endTime":"2018-11-29T18:48:24.527Z"},{"index":88,"src":"./assets/false/5-986.jpg","score":1,"duration_ms":672,"startTime":"2018-11-29T18:48:31.549Z","endTime":"2018-11-29T18:48:32.221Z"},{"index":89,"src":"./assets/icons/5-059.jpg","score":1,"duration_ms":834,"startTime":"2018-11-29T18:48:39.246Z","endTime":"2018-11-29T18:48:40.080Z"},{"index":90,"src":"./assets/false/5-984.jpg","score":1,"duration_ms":922,"startTime":"2018-11-29T18:48:47.096Z","endTime":"2018-11-29T18:48:48.018Z"},{"index":91,"src":"./assets/icons/5-067.jpg","score":1,"duration_ms":662,"startTime":"2018-11-29T18:48:55.039Z","endTime":"2018-11-29T18:48:55.701Z"},{"index":92,"src":"./assets/false/5-982.jpg","score":1,"duration_ms":767,"startTime":"2018-11-29T18:49:02.728Z","endTime":"2018-11-29T18:49:03.495Z"},{"index":93,"src":"./assets/false/5-981.jpg","score":1,"duration_ms":1752,"startTime":"2018-11-29T18:49:10.509Z","endTime":"2018-11-29T18:49:12.261Z"},{"index":94,"src":"./assets/icons/5-078.jpg","score":0,"duration_ms":738,"startTime":"2018-11-29T18:49:28.779Z","endTime":"2018-11-29T18:49:29.517Z"},{"index":95,"src":"./assets/icons/5-082.jpg","score":0,"duration_ms":991,"startTime":"2018-11-29T18:49:36.533Z","endTime":"2018-11-29T18:49:37.524Z"},{"index":96,"src":"./assets/false/5-978.jpg","score":0,"duration_ms":908,"startTime":"2018-11-29T18:49:44.543Z","endTime":"2018-11-29T18:49:45.451Z"},{"index":97,"src":"./assets/false/5-977.jpg","score":1,"duration_ms":1075,"startTime":"2018-11-29T18:49:52.471Z","endTime":"2018-11-29T18:49:53.546Z"},{"index":98,"src":"./assets/icons/5-094.jpg","score":0,"duration_ms":1138,"startTime":"2018-11-29T18:50:00.563Z","endTime":"2018-11-29T18:50:01.701Z"},{"index":99,"src":"./assets/icons/5-100.jpg","score":1,"duration_ms":1042,"startTime":"2018-11-29T18:50:08.723Z","endTime":"2018-11-29T18:50:09.765Z"},{"index":100,"src":"./assets/icons/6-002.jpg","score":1,"duration_ms":779,"startTime":"2018-11-29T18:50:16.786Z","endTime":"2018-11-29T18:50:17.565Z"},{"index":101,"src":"./assets/icons/6-005.jpg","score":1,"duration_ms":1002,"startTime":"2018-11-29T18:50:24.584Z","endTime":"2018-11-29T18:50:25.586Z"},{"index":102,"src":"./assets/icons/6-009.jpg","score":1,"duration_ms":833,"startTime":"2018-11-29T18:50:32.595Z","endTime":"2018-11-29T18:50:33.428Z"},{"index":103,"src":"./assets/false/6-996.jpg","score":1,"duration_ms":848,"startTime":"2018-11-29T18:50:40.452Z","endTime":"2018-11-29T18:50:41.300Z"},{"index":104,"src":"./assets/icons/6-020.jpg","score":1,"duration_ms":801,"startTime":"2018-11-29T18:50:48.325Z","endTime":"2018-11-29T18:50:49.126Z"},{"index":105,"src":"./assets/icons/6-024.jpg","score":1,"duration_ms":709,"startTime":"2018-11-29T18:50:56.143Z","endTime":"2018-11-29T18:50:56.852Z"},{"index":106,"src":"./assets/false/6-993.jpg","score":1,"duration_ms":738,"startTime":"2018-11-29T18:51:03.871Z","endTime":"2018-11-29T18:51:04.609Z"},{"index":107,"src":"./assets/icons/6-029.jpg","score":1,"duration_ms":796,"startTime":"2018-11-29T18:51:11.636Z","endTime":"2018-11-29T18:51:12.432Z"},{"index":108,"src":"./assets/icons/6-036.jpg","score":1,"duration_ms":547,"startTime":"2018-11-29T18:51:19.447Z","endTime":"2018-11-29T18:51:19.994Z"},{"index":109,"src":"./assets/false/6-990.jpg","score":1,"duration_ms":777,"startTime":"2018-11-29T18:51:27.016Z","endTime":"2018-11-29T18:51:27.793Z"},{"index":110,"src":"./assets/icons/6-042.jpg","score":1,"duration_ms":785,"startTime":"2018-11-29T18:51:34.818Z","endTime":"2018-11-29T18:51:35.603Z"},{"index":111,"src":"./assets/icons/6-047.jpg","score":1,"duration_ms":676,"startTime":"2018-11-29T18:51:42.626Z","endTime":"2018-11-29T18:51:43.302Z"},{"index":112,"src":"./assets/icons/6-052.jpg","score":1,"duration_ms":733,"startTime":"2018-11-29T18:51:50.323Z","endTime":"2018-11-29T18:51:51.056Z"},{"index":113,"src":"./assets/false/6-986.jpg","score":1,"duration_ms":749,"startTime":"2018-11-29T18:51:58.073Z","endTime":"2018-11-29T18:51:58.822Z"},{"index":114,"src":"./assets/icons/6-060.jpg","score":1,"duration_ms":580,"startTime":"2018-11-29T18:52:05.841Z","endTime":"2018-11-29T18:52:06.421Z"},{"index":115,"src":"./assets/icons/6-062.jpg","score":1,"duration_ms":804,"startTime":"2018-11-29T18:52:13.442Z","endTime":"2018-11-29T18:52:14.246Z"},{"index":116,"src":"./assets/false/6-983.jpg","score":1,"duration_ms":736,"startTime":"2018-11-29T18:52:21.266Z","endTime":"2018-11-29T18:52:22.002Z"},{"index":117,"src":"./assets/false/6-982.jpg","score":1,"duration_ms":1751,"startTime":"2018-11-29T18:52:29.026Z","endTime":"2018-11-29T18:52:30.777Z"},{"index":118,"src":"./assets/false/6-981.jpg","score":1,"duration_ms":756,"startTime":"2018-11-29T18:52:37.796Z","endTime":"2018-11-29T18:52:38.552Z"},{"index":119,"src":"./assets/false/6-980.jpg","score":1,"duration_ms":696,"startTime":"2018-11-29T18:52:45.571Z","endTime":"2018-11-29T18:52:46.267Z"},{"index":120,"src":"./assets/icons/7-002.jpg","score":1,"duration_ms":685,"startTime":"2018-11-29T18:52:53.282Z","endTime":"2018-11-29T18:52:53.967Z"},{"index":121,"src":"./assets/false/7-998.jpg","score":1,"duration_ms":684,"startTime":"2018-11-29T18:53:00.984Z","endTime":"2018-11-29T18:53:01.668Z"},{"index":122,"src":"./assets/false/7-997.jpg","score":1,"duration_ms":787,"startTime":"2018-11-29T18:53:08.685Z","endTime":"2018-11-29T18:53:09.472Z"},{"index":123,"src":"./assets/false/7-996.jpg","score":1,"duration_ms":727,"startTime":"2018-11-29T18:53:16.494Z","endTime":"2018-11-29T18:53:17.221Z"},{"index":124,"src":"./assets/false/7-995.jpg","score":1,"duration_ms":855,"startTime":"2018-11-29T18:53:24.243Z","endTime":"2018-11-29T18:53:25.098Z"},{"index":125,"src":"./assets/false/7-994.jpg","score":1,"duration_ms":843,"startTime":"2018-11-29T18:53:32.124Z","endTime":"2018-11-29T18:53:32.967Z"},{"index":126,"src":"./assets/icons/7-025.jpg","score":1,"duration_ms":1022,"startTime":"2018-11-29T18:53:39.978Z","endTime":"2018-11-29T18:53:41.000Z"},{"index":127,"src":"./assets/icons/7-030.jpg","score":1,"duration_ms":780,"startTime":"2018-11-29T18:53:48.017Z","endTime":"2018-11-29T18:53:48.797Z"},{"index":128,"src":"./assets/false/8-999.jpg","score":0,"duration_ms":1097,"startTime":"2018-11-29T18:53:55.822Z","endTime":"2018-11-29T18:53:56.919Z"},{"index":129,"src":"./assets/icons/8-005.jpg","score":0,"duration_ms":2693,"startTime":"2018-11-29T18:54:03.935Z","endTime":"2018-11-29T18:54:06.628Z"},{"index":130,"src":"./assets/icons/8-010.jpg","score":1,"duration_ms":2176,"startTime":"2018-11-29T18:54:13.643Z","endTime":"2018-11-29T18:54:15.819Z"},{"index":131,"src":"./assets/icons/8-013.jpg","score":1,"duration_ms":876,"startTime":"2018-11-29T18:54:22.836Z","endTime":"2018-11-29T18:54:23.712Z"},{"index":132,"src":"./assets/icons/8-018.jpg","score":0,"duration_ms":1517,"startTime":"2018-11-29T18:54:30.730Z","endTime":"2018-11-29T18:54:32.247Z"},{"index":133,"src":"./assets/false/8-994.jpg","score":1,"duration_ms":973,"startTime":"2018-11-29T18:54:39.263Z","endTime":"2018-11-29T18:54:40.236Z"},{"index":134,"src":"./assets/icons/8-027.jpg","score":1,"duration_ms":1780,"startTime":"2018-11-29T18:54:47.251Z","endTime":"2018-11-29T18:54:49.031Z"},{"index":135,"src":"./assets/false/8-992.jpg","score":1,"duration_ms":1016,"startTime":"2018-11-29T18:54:56.048Z","endTime":"2018-11-29T18:54:57.064Z"},{"index":136,"src":"./assets/icons/8-036.jpg","score":1,"duration_ms":607,"startTime":"2018-11-29T18:55:04.078Z","endTime":"2018-11-29T18:55:04.685Z"},{"index":137,"src":"./assets/icons/8-039.jpg","score":1,"duration_ms":1395,"startTime":"2018-11-29T18:55:11.698Z","endTime":"2018-11-29T18:55:13.093Z"},{"index":138,"src":"./assets/false/8-989.jpg","score":1,"duration_ms":783,"startTime":"2018-11-29T18:55:20.098Z","endTime":"2018-11-29T18:55:20.881Z"},{"index":139,"src":"./assets/icons/8-047.jpg","score":1,"duration_ms":943,"startTime":"2018-11-29T18:55:27.905Z","endTime":"2018-11-29T18:55:28.848Z"},{"index":140,"src":"./assets/icons/8-049.jpg","score":1,"duration_ms":1060,"startTime":"2018-11-29T18:55:35.872Z","endTime":"2018-11-29T18:55:36.932Z"},{"index":141,"src":"./assets/icons/8-055.jpg","score":1,"duration_ms":906,"startTime":"2018-11-29T18:55:43.953Z","endTime":"2018-11-29T18:55:44.859Z"},{"index":142,"src":"./assets/icons/8-059.jpg","score":1,"duration_ms":795,"startTime":"2018-11-29T18:55:51.881Z","endTime":"2018-11-29T18:55:52.676Z"},{"index":143,"src":"./assets/icons/8-063.jpg","score":1,"duration_ms":706,"startTime":"2018-11-29T18:55:59.698Z","endTime":"2018-11-29T18:56:00.404Z"},{"index":144,"src":"./assets/icons/8-066.jpg","score":0,"duration_ms":687,"startTime":"2018-11-29T18:56:07.428Z","endTime":"2018-11-29T18:56:08.115Z"},{"index":145,"src":"./assets/icons/8-072.jpg","score":1,"duration_ms":756,"startTime":"2018-11-29T18:56:15.125Z","endTime":"2018-11-29T18:56:15.881Z"},{"index":146,"src":"./assets/icons/8-074.jpg","score":1,"duration_ms":1190,"startTime":"2018-11-29T18:56:22.897Z","endTime":"2018-11-29T18:56:24.087Z"},{"index":147,"src":"./assets/false/8-980.jpg","score":1,"duration_ms":1121,"startTime":"2018-11-29T18:56:31.106Z","endTime":"2018-11-29T18:56:32.227Z"},{"index":148,"src":"./assets/false/8-979.jpg","score":1,"duration_ms":673,"startTime":"2018-11-29T18:56:39.245Z","endTime":"2018-11-29T18:56:39.918Z"},{"index":149,"src":"./assets/false/8-978.jpg","score":1,"duration_ms":1054,"startTime":"2018-11-29T18:56:46.935Z","endTime":"2018-11-29T18:56:47.989Z"},{"index":150,"src":"./assets/false/8-977.jpg","score":1,"duration_ms":789,"startTime":"2018-11-29T18:56:55.002Z","endTime":"2018-11-29T18:56:55.791Z"},{"index":151,"src":"./assets/false/8-976.jpg","score":1,"duration_ms":738,"startTime":"2018-11-29T18:57:02.808Z","endTime":"2018-11-29T18:57:03.546Z"},{"index":152,"src":"./assets/false/8-975.jpg","score":1,"duration_ms":933,"startTime":"2018-11-29T18:57:10.570Z","endTime":"2018-11-29T18:57:11.503Z"},{"index":153,"src":"./assets/false/8-974.jpg","score":1,"duration_ms":596,"startTime":"2018-11-29T18:57:18.525Z","endTime":"2018-11-29T18:57:19.121Z"}]}